<?xml version="1.0" encoding="UTF-8"?>

<!-- <PropertyList include="g4-jsbsim-cnf.xml"> -->
<PropertyList include="g4-yasim-cnf.xml">

  <sim>
    <description>Caudron G.IV</description>
    <author>Emmanuel BARANGER (3D/FDM)</author>

    <tags>
      <tag>bomber</tag>
      <tag>caudron</tag>
      <tag>1910s</tag>
      <tag>ww1</tag>
      <tag>fixed-gear</tag>
      <tag>tail-dragger</tag>
      <tag>biplane</tag>
      <tag>piston</tag>
      <tag>propeller</tag>
      <tag>fixed-pitch</tag>
      <tag>twin-engine</tag>
    </tags>

  </sim>


</PropertyList>

